repotea/__init__.py
repotea/api.py
repotea/args.py
repotea/cmds/__init__.py
repotea/cmds/_helpers.py
repotea/cmds/delete.py
repotea/cmds/list.py
repotea/cmds/new.py
repotea/cmds/orgs.py
repotea/repotea.py
repotea/utils.py
repotea-0.1.0.dist-info/entry_points.txt
repotea-0.1.0.dist-info/LICENSE
repotea-0.1.0.dist-info/WHEEL
repotea-0.1.0.dist-info/METADATA
repotea-0.1.0.dist-info/RECORD
